mediapipe_silicon-0.9.1.dist-info/RECORD
mediapipe_silicon-0.9.1.dist-info/LICENSE
mediapipe_silicon-0.9.1.dist-info/WHEEL
mediapipe_silicon-0.9.1.dist-info/top_level.txt
mediapipe_silicon-0.9.1.dist-info/METADATA
mediapipe/__init__.py
mediapipe/tasks/__init__.py
mediapipe/tasks/python/__init__.py
mediapipe/tasks/python/core/task_info.py
mediapipe/tasks/python/core/__init__.py
mediapipe/tasks/python/core/base_options.py
mediapipe/tasks/python/core/optional_dependencies.py
mediapipe/tasks/python/test/test_utils.py
mediapipe/tasks/python/test/__init__.py
mediapipe/tasks/python/test/vision/image_classifier_test.py
mediapipe/tasks/python/test/vision/__init__.py
mediapipe/tasks/python/test/vision/image_embedder_test.py
mediapipe/tasks/python/test/vision/image_segmenter_test.py
mediapipe/tasks/python/test/vision/hand_landmarker_test.py
mediapipe/tasks/python/test/vision/object_detector_test.py
mediapipe/tasks/python/test/audio/audio_classifier_test.py
mediapipe/tasks/python/test/audio/audio_embedder_test.py
mediapipe/tasks/python/test/audio/__init__.py
mediapipe/tasks/python/test/text/text_embedder_test.py
mediapipe/tasks/python/test/text/__init__.py
mediapipe/tasks/python/test/text/text_classifier_test.py
mediapipe/tasks/python/vision/image_classifier.py
mediapipe/tasks/python/vision/object_detector.py
mediapipe/tasks/python/vision/gesture_recognizer.py
mediapipe/tasks/python/vision/__init__.py
mediapipe/tasks/python/vision/hand_landmarker.py
mediapipe/tasks/python/vision/image_segmenter.py
mediapipe/tasks/python/vision/image_embedder.py
mediapipe/tasks/python/vision/core/__init__.py
mediapipe/tasks/python/vision/core/vision_task_running_mode.py
mediapipe/tasks/python/vision/core/image_processing_options.py
mediapipe/tasks/python/vision/core/base_vision_task_api.py
mediapipe/tasks/python/components/__init__.py
mediapipe/tasks/python/components/utils/__init__.py
mediapipe/tasks/python/components/utils/cosine_similarity.py
mediapipe/tasks/python/components/processors/__init__.py
mediapipe/tasks/python/components/processors/classifier_options.py
mediapipe/tasks/python/components/containers/audio_data.py
