Metadata-Version: 2.1
Name: mediapipe-silicon
Version: 0.9.1
Summary: MediaPipe is the simplest way for researchers and developers to build world-class ML solutions and applications for mobile, edge, cloud and the web.
Home-page: https://github.com/cansik/mediapipe-silicon
Author: The MediaPipe Authors
Author-email: mediapipe@google.com
License: Apache 2.0
Keywords: mediapipe
Platform: UNKNOWN
Classifier: Development Status :: 3 - Alpha
Classifier: Intended Audience :: Developers
Classifier: Intended Audience :: Education
Classifier: Intended Audience :: Science/Research
Classifier: License :: OSI Approved :: Apache Software License
Classifier: Operating System :: MacOS :: MacOS X
Classifier: Operating System :: Microsoft :: Windows
Classifier: Operating System :: POSIX :: Linux
Classifier: Programming Language :: Python :: 3.8
Classifier: Programming Language :: Python :: 3.9
Classifier: Programming Language :: Python :: 3.10
Classifier: Programming Language :: Python :: 3.11
Classifier: Programming Language :: Python :: 3 :: Only
Classifier: Topic :: Scientific/Engineering
Classifier: Topic :: Scientific/Engineering :: Artificial Intelligence
Classifier: Topic :: Software Development
Classifier: Topic :: Software Development :: Libraries
Classifier: Topic :: Software Development :: Libraries :: Python Modules
Requires-Dist: absl-py
Requires-Dist: attrs (>=19.1.0)
Requires-Dist: flatbuffers (>=2.0)
Requires-Dist: matplotlib
Requires-Dist: numpy
Requires-Dist: opencv-contrib-python
Requires-Dist: protobuf (<4,>=3.11)
